odoo/addons/account_bank_statement_import_transfer_move/README.rst
odoo/addons/account_bank_statement_import_transfer_move/__init__.py
odoo/addons/account_bank_statement_import_transfer_move/__manifest__.py
odoo/addons/account_bank_statement_import_transfer_move/i18n/account_bank_statement_import_transfer_move.pot
odoo/addons/account_bank_statement_import_transfer_move/models/__init__.py
odoo/addons/account_bank_statement_import_transfer_move/models/account_bank_statement_import.py
odoo/addons/account_bank_statement_import_transfer_move/models/account_journal.py
odoo/addons/account_bank_statement_import_transfer_move/readme/CONTRIBUTORS.rst
odoo/addons/account_bank_statement_import_transfer_move/readme/DESCRIPTION.rst
odoo/addons/account_bank_statement_import_transfer_move/static/description/icon.png
odoo/addons/account_bank_statement_import_transfer_move/static/description/index.html
odoo/addons/account_bank_statement_import_transfer_move/tests/__init__.py
odoo/addons/account_bank_statement_import_transfer_move/tests/test_statement.py
odoo/addons/account_bank_statement_import_transfer_move/view/account_journal.xml
odoo13_addon_account_bank_statement_import_transfer_move-13.0.1.0.1.dev10.dist-info/METADATA
odoo13_addon_account_bank_statement_import_transfer_move-13.0.1.0.1.dev10.dist-info/WHEEL
odoo13_addon_account_bank_statement_import_transfer_move-13.0.1.0.1.dev10.dist-info/top_level.txt
odoo13_addon_account_bank_statement_import_transfer_move-13.0.1.0.1.dev10.dist-info/RECORD
